{"id":117336,"strId":"BGDUO31_212","cardType":"minion","name":"Mantid King","nameCN":"螳螂妖国王","text":"在你的队伍<b>传递</b>后，\n直到下个回合，随机从<b>烈毒</b>，<b>嘲讽</b>或<b>圣盾</b>中获得一种。","mechanics":["TRIGGER_VISUAL"],"referencedTags":["DIVINE_SHIELD","TAUNT","VENOMOUS"],"img":"https://battlegrounds.oss.gamerhub.cn/all_images/32.2.4.221850/BGDUO31_212_battlegroundsImage.png","art":"https://battlegrounds.oss.gamerhub.cn/all_images/32.2.4.221850/BGDUO31_212_cardArtFromHsJson256x.png","DuoGameExclusive":true,"tier":4,"health":3,"attack":3,"minionTypes":["none"],"minionTypesCN":["中立"],"upgradeCard":{"id":117337,"strId":"BGDUO31_212_G","cardType":"minion","name":"Mantid King","nameCN":"螳螂妖国王","text":"在你的队伍<b>传递</b>后，随机从<b>烈毒</b>，<b>嘲讽</b>或<b>圣盾</b>中获得一种。","mechanics":["TRIGGER_VISUAL"],"referencedTags":["DIVINE_SHIELD","TAUNT","VENOMOUS"],"img":"https://battlegrounds.oss.gamerhub.cn/all_images/32.2.4.221850/BGDUO31_212_G_battlegroundsImageGold.png","art":"https://battlegrounds.oss.gamerhub.cn/all_images/32.2.4.221850/BGDUO31_212_G_cardArtFromHsJson256x.png","tier":4,"health":6,"attack":6,"minionTypes":["none"],"minionTypesCN":["中立"]}}