{"id":119988,"strId":"BG32_232","cardType":"minion","name":"Thieving Rascal","nameCN":"偷金捣蛋鬼","text":"在你的回合开始时，获得1枚铸币。每有一个友方金色随从，重复一次。","mechanics":["TRIGGER_VISUAL"],"referencedTags":[],"img":"https://battlegrounds.oss.gamerhub.cn/all_images/32.2.4.221850/BG32_232_battlegroundsImage.png","art":"https://battlegrounds.oss.gamerhub.cn/all_images/32.2.4.221850/BG32_232_cardArtFromHsJson256x.png","tier":4,"health":6,"attack":5,"minionTypes":["pirate"],"minionTypesCN":["海盗"],"upgradeCard":{"id":119989,"strId":"BG32_232_G","cardType":"minion","name":"Thieving Rascal","nameCN":"偷金捣蛋鬼","text":"在你的回合开始时，获得2枚铸币。每有一个友方金色随从，重复一次。","mechanics":["TRIGGER_VISUAL"],"referencedTags":[],"img":"https://battlegrounds.oss.gamerhub.cn/all_images/32.2.4.221850/BG32_232_G_battlegroundsImageGold.png","art":"https://battlegrounds.oss.gamerhub.cn/all_images/32.2.4.221850/BG32_232_G_cardArtFromHsJson256x.png","tier":4,"health":12,"attack":10,"minionTypes":["pirate"],"minionTypesCN":["海盗"]}}