{"id":117359,"strId":"BGDUO31_211","cardType":"minion","name":"Transport Reactor","nameCN":"转运反应堆","text":"<b>磁力</b>。在本局对战中，你的队伍每<b>传递</b>过一次，便拥有+1/+1<i>（无论本随从在哪）。</i>","mechanics":["AURA","MAGNETIC"],"referencedTags":[],"img":"https://battlegrounds.oss.gamerhub.cn/all_images/32.2.4.221850/BGDUO31_211_battlegroundsImage.png","art":"https://battlegrounds.oss.gamerhub.cn/all_images/32.2.4.221850/BGDUO31_211_cardArtFromHsJson256x.png","DuoGameExclusive":true,"tier":6,"health":1,"attack":1,"minionTypes":["mech"],"minionTypesCN":["机械"],"upgradeCard":{"id":117360,"strId":"BGDUO31_211_G","cardType":"minion","name":"Transport Reactor","nameCN":"转运反应堆","text":"<b>磁力</b>。在本局对战中，你的队伍每<b>传递</b>过一次，便拥有+2/+2<i>（无论本随从在哪）。</i>","mechanics":["AURA","MAGNETIC"],"referencedTags":[],"img":"https://battlegrounds.oss.gamerhub.cn/all_images/32.2.4.221850/BGDUO31_211_G_battlegroundsImageGold.png","art":"https://battlegrounds.oss.gamerhub.cn/all_images/32.2.4.221850/BGDUO31_211_G_cardArtFromHsJson256x.png","tier":6,"health":2,"attack":2,"minionTypes":["mech"],"minionTypesCN":["机械"]}}